netneural/__init__.py
netneural/network/__init__.py
netneural/network/feature_scaling.py
netneural/network/metrics.py
netneural/network/nn.py
netneural/network/one_hot_encoder.py
netneural/network/plot_lib.py
netneural/optimizers/__init__.py
netneural/optimizers/adam_optimizer.py
netneural/pca/__init__.py
netneural/pca/pca.py
netneural/session/__init__.py
netneural/session/data_loader.py
netneural/session/nn_session_util.py
tests/__init__.py
tests/test_one_hot_encoder.py
netneural-0.0.5.dist-info/LICENSE
netneural-0.0.5.dist-info/METADATA
netneural-0.0.5.dist-info/WHEEL
netneural-0.0.5.dist-info/top_level.txt
netneural-0.0.5.dist-info/RECORD
